setup.py
remotecv_aws/__init__.py
remotecv_aws/bucket.py
remotecv_aws/loader.py
remotecv_aws.egg-info/PKG-INFO
remotecv_aws.egg-info/SOURCES.txt
remotecv_aws.egg-info/dependency_links.txt
remotecv_aws.egg-info/not-zip-safe
remotecv_aws.egg-info/requires.txt
remotecv_aws.egg-info/top_level.txt