Metadata-Version: 1.0
Name: remotecv-aws
Version: 0.1
Summary: Remotecv AWS loader
Home-page: UNKNOWN
Author: Edu Heraiz @ APSL
Author-email: gshark@gmail.com
License: UNKNOWN
Platform: UNKNOWN
